entium/__init__.py
entium/__main__.py
entium/converter.py
entium/cesium/__init__.py
entium/cesium/config.py
entium/cesium/tiles.py
entium/cesium/tileset.py
entium-0.1.4.dist-info/METADATA
entium-0.1.4.dist-info/RECORD
entium-0.1.4.dist-info/WHEEL
entium-0.1.4.dist-info/entry_points.txt
entium-0.1.4.dist-info/top_level.txt
