Metadata-Version: 2.1
Name: entium
Version: 0.1.4
Summary: A command line tool to read entwine's convert into Cesium 3DTiles
Home-page: https://github.com/commaai/entium
Author: Brandon Barker
Author-email: brandon@comma.ai
License: MIT LICENSE
Keywords: cli,entwine,cesium,converter
Platform: UNKNOWN
Classifier: Intended Audience :: Developers
Classifier: Topic :: Utilities
Classifier: License :: Public Domain
Classifier: Natural Language :: English
Classifier: Operating System :: OS Independent
Classifier: Development Status :: 4 - Beta
Classifier: Programming Language :: Python :: 2.7
Requires-Dist: enum34 (==1.1.6)
Requires-Dist: numpy (==1.14.5)
